{
  "service": {
    "name": "notification-slack-config",
    "version": "1",
    "moduleName": "slack"
  },
  "tables": {
    "webhook": {
      "docs": {
        "name": "Webhook",
        "summary": "Configuration for webhook table",
        "version": "1.0.0"
      },
      "apis": {},
      "store": {
        "read": "sql,eventstream,redis",
        "write": "sql,eventstream,redis",
        "query": "sql,eventstream,redis"
      },
      "redis": {
        "prefix": "",
        "version": "1.0",
        "category": "notification:webhook-config.webhook.v1",
        "ttl": 3600,
        "hash": true,
        "aggregate": "webhook"
      },
      "eventstream": {
        "boundedContext": "notification",
        "aggregate": "webhook",
        "version": "v1",
        "stream": "notification.webhookConfig.webhook",
        "createdEvent": "NotificationWebhookConfigWebhookCreated.v1",
        "updatedEvent": "NotificationWebhookConfigWebhookUpdated.v1",
        "deletedEvent": "NotificationWebhookConfigWebhookDeleted.v1"
      },
      "cols": {
        "id": {},
        "name": {},
        "description": {},
        "targetUrl": {},
        "method": {},
        "headers": {},
        "signingSecretRef": {},
        "status": {},
        "verifyTls": {},
        "requestTimeoutMs": {},
        "connectTimeoutMs": {},
        "rateLimitPerMinute": {},
        "webhookEventType": {}
      },
      "permissions": {
        "bulk": [
          "update",
          "delete",
          "import"
        ],
        "adminOverride": true,
        "auditView": true,
        "custom": []
      }
    },
    "config": {
      "docs": {
        "name": "Config",
        "summary": "Configuration for config table",
        "version": "1.0.0"
      },
      "apis": {},
      "store": {
        "read": "sql,eventstream,redis",
        "write": "sql,eventstream,redis",
        "query": "sql,eventstream,redis"
      },
      "redis": {
        "prefix": "",
        "version": "1.0",
        "category": "notification:webhook-config.config.v1",
        "ttl": 3600,
        "hash": true,
        "aggregate": "config"
      },
      "eventstream": {
        "boundedContext": "notification",
        "aggregate": "config",
        "version": "v1",
        "stream": "notification.webhookConfig.config",
        "createdEvent": "NotificationWebhookConfigConfigCreated.v1",
        "updatedEvent": "NotificationWebhookConfigConfigUpdated.v1",
        "deletedEvent": "NotificationWebhookConfigConfigDeleted.v1"
      },
      "cols": {
        "id": {},
        "webhookId": {},
        "tenantId": {},
        "strategy": {},
        "maxRetryAttempts": {},
        "retryBackoffSeconds": {},
        "retryStrategy": {},
        "backoffJitterPct": {},
        "requestTimeoutMs": {},
        "connectTimeoutMs": {},
        "signatureAlgorithm": {},
        "includeTimestampHeader": {},
        "maxConcurrent": {},
        "dlqEnabled": {},
        "dlqMaxAgeSeconds": {},
        "ordering": {},
        "defaultLocale": {},
        "metadata": {}
      },
      "permissions": {
        "bulk": [
          "update",
          "delete",
          "import"
        ],
        "adminOverride": true,
        "auditView": true,
        "custom": []
      }
    }
  },
  "docs": {
    "summary": ""
  }
}